LICENSE
README.md
setup.py
trainyolo/__init__.py
trainyolo/cli.py
trainyolo/cli_functions.py
trainyolo/cli_options.py
trainyolo/client.py
trainyolo/utils/__init__.py
trainyolo/utils/bbox.py
trainyolo/utils/colormap.py
trainyolo/utils/image_ops.py
trainyolo/utils/mask_utils.py
trainyolo/utils/ocr.py
trainyolo/utils/rle.py
trainyolo/utils/rle_cython.c
trainyolo/utils/rle_cython.pyx
trainyolo/utils/segment.py
trainyolo/utils/yolonas.py
trainyolo/utils/yolov5.py
trainyolo/utils/yolov8.py
trainyolo_py.egg-info/PKG-INFO
trainyolo_py.egg-info/SOURCES.txt
trainyolo_py.egg-info/dependency_links.txt
trainyolo_py.egg-info/entry_points.txt
trainyolo_py.egg-info/requires.txt
trainyolo_py.egg-info/top_level.txt