Metadata-Version: 2.1
Name: trainyolo-py
Version: 0.0.22
Summary: Python sdk and cli for trainyolo
Home-page: https://github.com/trainyolo/trainyolo-py
Author: trainyolo
Author-email: info@trainyolo.com
Classifier: Programming Language :: Python :: 3
Classifier: License :: OSI Approved :: MIT License
Requires-Python: >=3.6
License-File: LICENSE
Requires-Dist: tqdm
Requires-Dist: requests
Requires-Dist: argcomplete
Requires-Dist: PyYAML
Requires-Dist: numpy
Requires-Dist: opencv-python
